pyofw/__init__.py
pyofw/config.py
pyofw/model_input.py
pyofw/network_input.py
pyofw/support.py
pyofw/template/Getting_Started.ipynb
pyofw/template/example_minimal.py
pyofw/template/example_with_comments.py
pyofw/tools/__init__.py
pyofw/tools/cmd.py
pyofw/typings/pyofw/ISystem.pyi
pyofw/typings/pyofw/OpenFlows.pyi
pyofw/typings/pyofw/__init__.py
pyofw/typings/pyofw/Haestad/IDomain.pyi
pyofw/typings/pyofw/Haestad/ILicensingFacade.pyi
pyofw/typings/pyofw/Haestad/__init__.py
pyofw/typings/pyofw/Haestad/Calculations/IPressure.pyi
pyofw/typings/pyofw/Haestad/Calculations/__init__.py
pyofw/typings/pyofw/Haestad/Domain/ModelingObjects/IWater.pyi
pyofw/typings/pyofw/Haestad/Domain/ModelingObjects/__init__.py
pyofw/typings/pyofw/Haestad/Domain/ModelingObjects/Water/Enumerations.pyi
pyofw/typings/pyofw/Haestad/Domain/ModelingObjects/Water/__init__.py
pyofw/typings/pyofw/Haestad/Domain/ModelingObjects/Water/Support/IPumpDefinitions.pyi
pyofw/typings/pyofw/Haestad/Domain/ModelingObjects/Water/Support/__init__.py
pyofw/typings/pyofw/Haestad/Support/ISupport.pyi
pyofw/typings/pyofw/Haestad/Support/IUnits.pyi
pyofw/typings/pyofw/Haestad/Support/IUser.pyi
pyofw/typings/pyofw/Haestad/Support/__init__.py
pyofw/typings/pyofw/OpenFlows/IAnalysis.pyi
pyofw/typings/pyofw/OpenFlows/IApplication.pyi
pyofw/typings/pyofw/OpenFlows/ILicensing.pyi
pyofw/typings/pyofw/OpenFlows/IUnits.pyi
pyofw/typings/pyofw/OpenFlows/IWater.pyi
pyofw/typings/pyofw/OpenFlows/__init__.py
pyofw/typings/pyofw/OpenFlows/Domain/IDataObjects.pyi
pyofw/typings/pyofw/OpenFlows/Domain/IModelingElements.pyi
pyofw/typings/pyofw/OpenFlows/Domain/__init__.py
pyofw/typings/pyofw/OpenFlows/Domain/ModelingElements/IAlternatives.pyi
pyofw/typings/pyofw/OpenFlows/Domain/ModelingElements/ICollections.pyi
pyofw/typings/pyofw/OpenFlows/Domain/ModelingElements/IComponents.pyi
pyofw/typings/pyofw/OpenFlows/Domain/ModelingElements/INetworkElements.pyi
pyofw/typings/pyofw/OpenFlows/Domain/ModelingElements/ISupport.pyi
pyofw-10.4.dist-info/LICENSE
pyofw-10.4.dist-info/METADATA
pyofw-10.4.dist-info/WHEEL
pyofw-10.4.dist-info/entry_points.txt
pyofw-10.4.dist-info/top_level.txt
pyofw-10.4.dist-info/RECORD
