Metadata-Version: 2.1
Name: pyofw
Version: 10.4
Summary: Bentley OpenFlows API stub files plus a few py files
Home-page: https://github.com/worthapenny/pyofw
Author: Akshaya Niraula
Author-email: Akshaya.Niraula@gmail.com
Project-URL: Bug Tracker, https://github.com/worthapenny/pyofw/issues
Classifier: Programming Language :: Python :: 3
Classifier: License :: OSI Approved :: MIT License
Classifier: Operating System :: Microsoft :: Windows
Classifier: Development Status :: 4 - Beta
Requires-Python: >=3.6
License-File: LICENSE
Requires-Dist: networkx
Requires-Dist: pandas
Requires-Dist: pythonnet
Requires-Dist: numpy
Requires-Dist: pyproj
Provides-Extra: dev
Requires-Dist: pytest >=3.7 ; extra == 'dev'
Requires-Dist: wheel ; extra == 'dev'
Requires-Dist: twine ; extra == 'dev'
